harmonicsonification/__init__.py
harmonicsonification-0.1.0.dist-info/licenses/LICENSE
harmonicsonification-0.1.0.dist-info/METADATA
harmonicsonification-0.1.0.dist-info/WHEEL
harmonicsonification-0.1.0.dist-info/top_level.txt
harmonicsonification-0.1.0.dist-info/RECORD
